{
  "date": "2026-06-15",
  "items": [
    {
      "hash": "c8693601b21c6442c4a2205bd12ef53c",
      "title": "Christine Lagarde: Money in transition",
      "summary": "",
      "link": "https://www.ecb.europa.eu//press/key/date/2026/html/ecb.sp260615~35e6c6c4de.en.html",
      "source": "ECB",
      "score": 9,
      "weight": 5,
      "status": "new",
      "ts": "2026-06-15T12:32:43.276838+05:00",
      "age_min": 2.7
    },
    {
      "hash": "774ded9da9e5c5c90eca8c0ab99cd8e0",
      "title": "Macron to pull out the stops to keep Trump at G7 gathering",
      "summary": "First rich nations summit since Iran war launched, a make-or-break British by-election, Warsh chairs his first FOMC meeting",
      "link": "https://www.ft.com/content/c6e9173b-0426-486b-bbba-124aeb28ee89",
      "source": "FT",
      "score": 10,
      "weight": 4,
      "status": "new",
      "ts": "2026-06-15T00:03:12.933266+05:00",
      "age_min": 108.2
    },
    {
      "hash": "7e38a7bfd35a02d399b413cb9154be2c",
      "title": "UK intercepts Russian shadow fleet oil tanker in English Channel",
      "summary": "Prime minister hails ‘yet another blow to Russia’ as part of effort to clamp down on those fuelling Ukraine war",
      "link": "https://www.ft.com/content/3fb01bb7-791f-449c-96c6-a75fd39220fd",
      "source": "FT",
      "score": 10,
      "weight": 4,
      "status": "new",
      "ts": "2026-06-14T21:32:52.958840+05:00",
      "age_min": 3.0
    },
    {
      "hash": "fccdd037c8fbe79594ac68ede8708893",
      "title": "Warsh Caught Between Trump and Bond Market Betting on Rate Hikes",
      "summary": "",
      "link": "https://finance.yahoo.com/economy/policy/articles/warsh-caught-between-trump-bond-170000260.html",
      "source": "GDELT/FED_ECB",
      "score": 10,
      "weight": 4,
      "status": "new",
      "ts": "2026-06-15T00:16:45.609321+05:00",
      "age_min": 31.8
    },
    {
      "hash": "7da14171fa14593da73aae5a6c297083",
      "title": "EXCLUSIVE : Nicholas Irving : War at 100 Days , Could Last to 2027 , Trump Avoids Escalation ( Full Interview )",
      "summary": "",
      "link": "https://www.vladtv.com/article/315245/nicholas-irving-war-at-100-days-could-last-to-2027-trump-avoids",
      "source": "GDELT/CONFLICTS",
      "score": 10,
      "weight": 4,
      "status": "new",
      "ts": "2026-06-15T00:45:50.582345+05:00",
      "age_min": 15.8
    },
    {
      "hash": "634bcee4994a8049b849405f36bd520b",
      "title": "Deal is reached to end Iran war and Trump orders stop to US naval blockade",
      "summary": "",
      "link": "https://www.thestar.com/news/world/middle-east/qatari-mediators-travel-to-tehran-for-final-touches-on-a-possible-deal-to-end-war/article_4b95573b-fecd-509c-880d-0b2f46fba404.html",
      "source": "GDELT/CONFLICTS",
      "score": 10,
      "weight": 4,
      "status": "new",
      "ts": "2026-06-15T04:15:43.239029+05:00",
      "age_min": 30.7
    },
    {
      "hash": "fb241b783880c631961b5fd20f325d83",
      "title": "UK, France, Germany Ready to Lift Relevant Iran Sanctions",
      "summary": "“We are prepared to lift relevant sanctions in response to clear, verifiable steps by Iran on its nuclear programme,” according to a joint statement from the leaders of the UK, France, Germany and Italy.",
      "link": "https://www.bloomberg.com/news/articles/2026-06-14/uk-france-germany-ready-to-lift-relevant-sanctions",
      "source": "Bloomberg",
      "score": 10,
      "weight": 4,
      "status": "new",
      "ts": "2026-06-15T04:32:48.428661+05:00",
      "age_min": 30.4
    },
    {
      "hash": "37fcafb9f821c4e2ab32f2af41829ac6",
      "title": "Japanese Stocks Set to Rise After US-Iran Peace Deal Reached",
      "summary": "Japanese stocks are set to gain after President Donald Trump said the US and Iran have reached a peace deal, raising hopes the Middle East war is nearing an end and the Strait of Hormuz will reopen.",
      "link": "https://www.bloomberg.com/news/articles/2026-06-14/japanese-stocks-set-to-rise-after-us-iran-peace-deal-reached",
      "source": "Bloomberg",
      "score": 10,
      "weight": 4,
      "status": "new",
      "ts": "2026-06-15T04:32:48.427339+05:00",
      "age_min": 23.0
    },
    {
      "hash": "0222fe819f257e45aeeb301b5fe2641e",
      "title": "Deal is reached to end Iran war and Trump orders stop to US naval blockade",
      "summary": "",
      "link": "https://www.csmonitor.com/World/2026/0614/US-and-Iran-reach-deal-to-end-war-stop-naval-blockade",
      "source": "GDELT/MIDEAST",
      "score": 10,
      "weight": 4,
      "status": "new",
      "ts": "2026-06-15T04:46:06.621299+05:00",
      "age_min": 46.1
    },
    {
      "hash": "3682c0975b083bb3909e53733093f2f1",
      "title": "US and Iran Agree to Deal Halting War",
      "summary": "The US and Iran reached an interim agreement to reopen the Strait of Hormuz, halting a war that killed thousands of people and setting the stage for negotiations on the fate of Iran's nuclear program. (Source: Bloomberg)",
      "link": "https://www.bloomberg.com/news/videos/2026-06-14/us-and-iran-agree-to-deal-halting-war-video",
      "source": "Bloomberg",
      "score": 10,
      "weight": 4,
      "status": "new",
      "ts": "2026-06-15T05:03:12.384980+05:00",
      "age_min": 13.5
    },
    {
      "hash": "67649ab48234bc41859f1cd7d9da2543",
      "title": "US - Iran war ends : How peace deal impacts Strait of Hormuz , nuclear program",
      "summary": "",
      "link": "https://www.fox5ny.com/news/us-iran-war-ends-how-peace-deal-impacts-strait-hormuz-nuclear-program",
      "source": "GDELT/CONFLICTS",
      "score": 10,
      "weight": 4,
      "status": "new",
      "ts": "2026-06-15T05:15:42.519356+05:00",
      "age_min": -1409.3
    },
    {
      "hash": "bfaefcca971129fec5c78eae095aea10",
      "title": "Vanguard's Wang on Iran-US Deal Economic Impact",
      "summary": "Qian Wang, Chief APAC Economist at Vanguard Group, discusses the US and Iran agreement to a deal that will halt war and says while there is still significant uncertainty around how sustainable the current deal is, it could boost the outlook for the global economy.\nShe speaks with Shery Ahn and Haidi Stroud Watts on \"Bloomberg: The Asia Trade\". (Source: Bloomberg)",
      "link": "https://www.bloomberg.com/news/videos/2026-06-15/vanguard-s-wang-on-iran-us-deal-economic-impact-video",
      "source": "Bloomberg",
      "score": 10,
      "weight": 4,
      "status": "new",
      "ts": "2026-06-15T06:03:22.574841+05:00",
      "age_min": 20.9
    },
    {
      "hash": "a4e2760885bf867f72fb4b4869f3745d",
      "title": "AGSI's Roebuck on US-Iran Deal",
      "summary": "William Roebuck, Former US Ambassador to Bahrian and Executive Vice President at Arab Gulf States Institute, discusses his outlook for the agreement between US and Iran to halt the war. He says the conflict is \"moving into a new stage\" and that is towards a \"diplomatic track\".\nHe speaks with Shery Ahn and Haidi Stroud Watts on \"Bloomberg: The Asia Trade\". (Source: Bloomberg)",
      "link": "https://www.bloomberg.com/news/videos/2026-06-15/agsi-s-roebuck-on-us-iran-deal-video",
      "source": "Bloomberg",
      "score": 10,
      "weight": 4,
      "status": "new",
      "ts": "2026-06-15T06:03:22.573825+05:00",
      "age_min": 13.9
    },
    {
      "hash": "4b3453c2027d9dc17e059c963d711a8e",
      "title": "Deal is reached to end Iran war and Trump orders stop to US naval blockade",
      "summary": "",
      "link": "https://www.wfmz.com/news/deal-is-reached-to-end-iran-war-and-trump-orders-stop-to-us-naval-blockade/article_c5f85a52-844b-5301-8ce1-fd1e6d736a6a.html",
      "source": "GDELT/CONFLICTS",
      "score": 10,
      "weight": 4,
      "status": "new",
      "ts": "2026-06-15T06:01:01.723267+05:00",
      "age_min": 31.0
    },
    {
      "hash": "a024342a2bd9872bf3c54987258d12a1",
      "title": "Deal is reached to end Iran war ; Trump orders stop to US naval blockade",
      "summary": "",
      "link": "https://www.mercurynews.com/2026/06/14/deal-is-reached-to-end-iran-war-trump-orders-stop-to-us-naval-blockade/",
      "source": "GDELT/MIDEAST",
      "score": 10,
      "weight": 4,
      "status": "new",
      "ts": "2026-06-15T06:16:11.644914+05:00",
      "age_min": 46.2
    },
    {
      "hash": "7480a1b4ddff60a231ffc06bd2f71019",
      "title": "Treasuries Rally as Traders Trim Fed Hike Bets After Iran Deal",
      "summary": "Treasuries advanced across the curve as investors dialed back expectations for Federal Reserve interest-rate hikes following news of a deal to end the Iran war.",
      "link": "https://www.bloomberg.com/news/articles/2026-06-15/treasuries-rally-as-traders-trim-fed-hike-bets-after-iran-deal",
      "source": "Bloomberg",
      "score": 10,
      "weight": 4,
      "status": "new",
      "ts": "2026-06-15T06:32:50.808815+05:00",
      "age_min": 33.4
    },
    {
      "hash": "7583a876db9e997299a0e5e026479cc5",
      "title": "Korea’s JoongAng Seeks Rehabilitation After Broadcaster Default",
      "summary": "South Korean media giant JoongAng Group has filed for court rehabilitation after its broadcaster defaulted on a loan, with the company hit by financial strain linked to its purchase of expensive sports broadcasting rights acquired at the peak of the media market.",
      "link": "https://www.bloomberg.com/news/articles/2026-06-15/korea-media-giant-seeks-rehabilitation-after-broadcaster-default",
      "source": "Bloomberg",
      "score": 10,
      "weight": 4,
      "status": "new",
      "ts": "2026-06-15T07:02:57.230074+05:00",
      "age_min": 43.2
    },
    {
      "hash": "611e6bd049d9d2fec0214323baad7849",
      "title": "A tentative deal is reached to end the Iran war and Trump orders a stop to the US naval blockade",
      "summary": "",
      "link": "https://www.republicanherald.com/2026/06/14/a-tentative-deal-is-reached-to-end-the-iran-war-and-trump-orders-a-stop-to-the-us-naval-blockade/",
      "source": "GDELT/ENERGY",
      "score": 10,
      "weight": 4,
      "status": "new",
      "ts": "2026-06-15T07:02:12.713908+05:00",
      "age_min": 17.2
    },
    {
      "hash": "ed3498c23dbacc1a4de2325ca5b32dfe",
      "title": "US-Iran deal eases uncertainty over the war - but there is much still to play out",
      "summary": "Pakistan says the deal includes Lebanon, but recent ceasefires there have failed to take hold.",
      "link": "https://www.bbc.com/news/articles/cd952n4qz2qo?at_medium=RSS&at_campaign=rss",
      "source": "BBC World",
      "score": 10,
      "weight": 4,
      "status": "new",
      "ts": "2026-06-15T07:47:04.725086+05:00",
      "age_min": 69.3
    },
    {
      "hash": "35941dad0c73e8987c9946bcfa2ea592",
      "title": "SVB Energy's Vakhshouri on the Outlook for Oil Prices",
      "summary": "Sara Vakhshouri, founder of SVB Energy International, says the oil market has adapted to the Strait of Hormuz disruption and prices could fall to pre-war levels if the waterway \"truly\" reopens.\n\nShe speaks with David Ingles and Yvonne Man on Bloomberg's The China Show. (Source: Bloomberg)",
      "link": "https://www.bloomberg.com/news/videos/2026-06-15/svb-energy-s-vakhshouri-on-the-outlook-for-oil-prices-video",
      "source": "Bloomberg",
      "score": 10,
      "weight": 4,
      "status": "new",
      "ts": "2026-06-15T08:03:21.952201+05:00",
      "age_min": 16.8
    }
  ],
  "updated": "2026-06-15T17:03:58.571310+05:00"
}