{
  "updated": "2026-07-07T15:36:04.631874+05:00",
  "items": [
    {
      "hash": "96f36f44bffcc8ec2008eb766016e616",
      "title": "ਚੀਨ ਨੇ ਪਰਮਾਣੂ ਪਣਡੁੱਬੀ ਤੋਂ ਕੀਤਾ ਬੈਲਿਸਟਿਕ ਮਿਜ਼ਾਈਲ ਦਾ ਸਫਲ ਪ੍ਰੀਖਣ ; ਜਾਪਾਨ ਤੇ ਆਸਟ੍ਰੇਲੀਆ ਵਲੋਂ ਤਿੱਖੀ ਆਲੋਚਨਾ - China Successfully Tests Ballistic Missile from Nuclear Submarine in Pacific Ocean",
      "summary": "",
      "link": "https://www.punjabijagran.com/world/other-country-china-successfully-tests-ballistic-missile-from-nuclear-submarine-in-pacific-ocean-9652029.html",
      "source": "GDELT/CONFLICTS",
      "score": 10,
      "weight": 4,
      "status": "new",
      "ts": "2026-07-07T15:01:49.928701+05:00",
      "age_min": 31.8
    },
    {
      "hash": "4d658ee4cbdbcc19bc19cc191e891485",
      "title": "Has the Iran war changed the world order? Submit a question to Gideon Rachman",
      "summary": "Take part in a live Ask an Expert Q&amp;A with the FT’s chief foreign affairs commentator today at 10.30am BST",
      "link": "https://www.ft.com/content/c1fd3bf3-20a1-44f0-8a6c-861a1db469be",
      "source": "FT",
      "score": 10,
      "weight": 4,
      "status": "new",
      "ts": "2026-07-07T13:18:05.181723+05:00",
      "age_min": 1.4
    },
    {
      "hash": "ee5946d68be050452a54c19f2aa51637",
      "title": "ലക്ഷ്യം അമേരിക്കയോ ?, പസഫിക് സമുദ്രത്തിൽ ചൈനയുടെ ദീർഘദൂര ബാലിസ്റ്റിക് മിസൈൽ പരീക്ഷണം | China Tests Long - range Ballistic Missile in Pacific , Sparks US Concern Over Nuclear Build - up",
      "summary": "",
      "link": "https://www.madhyamam.com/world/china-tests-long-range-ballistic-missile-in-pacific-sparks-us-concern-over-nuclear-build-up-1535129",
      "source": "GDELT/CONFLICTS",
      "score": 10,
      "weight": 4,
      "status": "new",
      "ts": "2026-07-07T11:46:30.892600+05:00",
      "age_min": 31.5
    },
    {
      "hash": "8cb47c0a06fb39f9ff1524ba12af1d9d",
      "title": "Покушение на Ермолаева в Киеве обнаружили закопанное тело подозреваемой Фокус",
      "summary": "",
      "link": "https://focus.ua/ukraine/760057-pokushenie-na-ermolaeva-v-kieve-obnaruzhili-zakopannoe-telo-podozrevaemoy-fokus",
      "source": "GDELT/TERRORISM",
      "score": 9,
      "weight": 4,
      "status": "new",
      "ts": "2026-07-07T15:33:12.869167+05:00",
      "age_min": 33.2
    },
    {
      "hash": "bcdc10bb32be8267cf79c793405fdb45",
      "title": "Покушение на Макрона ? В Дамаске взорвался заминированный автомобиль - взрыв попал в объективы камер",
      "summary": "",
      "link": "https://www.9tv.co.il/item/256347",
      "source": "GDELT/TERRORISM",
      "score": 9,
      "weight": 4,
      "status": "new",
      "ts": "2026-07-07T15:33:12.863204+05:00",
      "age_min": 63.2
    },
    {
      "hash": "645619153d24973b9b628e2bd1fb0923",
      "title": "Покушение на бизнесмена Вадима Ермолаева – под Киевом нашли мертвой подозреваемую",
      "summary": "",
      "link": "https://24tv.ua/ru/pokushenie-na-biznesmena-vadima-ermolaeva-pod-kievom-nashli-mertvoj-podozrevaemuju_n3101196",
      "source": "GDELT/TERRORISM",
      "score": 9,
      "weight": 4,
      "status": "new",
      "ts": "2026-07-07T14:16:13.970107+05:00",
      "age_min": 61.2
    },
    {
      "hash": "b1cc556695afc50db404f06ed921753d",
      "title": "Czech June Inflation Slows More Than Expected After Rate Hike",
      "summary": "Czech inflation slowed more than expected below target last month, underscoring the central bank’s monetary-policy dilemma after it raised interest rates.",
      "link": "https://www.bloomberg.com/news/articles/2026-07-07/czech-june-inflation-slows-more-than-expected-after-rate-hike",
      "source": "Bloomberg",
      "score": 9,
      "weight": 4,
      "status": "new",
      "ts": "2026-07-07T12:47:48.481028+05:00",
      "age_min": 22.5
    },
    {
      "hash": "9ba5b7066cbf88699fbbe93a418dcdb7",
      "title": "Ukraine Invasion Day 1 , 594 : Omsk Refinery hit , 2500 km from the border",
      "summary": "",
      "link": "https://www.dailykos.com/stories/2026/7/6/800066032/community/1594/",
      "source": "GDELT/RUSSIA_UA",
      "score": 9,
      "weight": 4,
      "status": "new",
      "ts": "2026-07-07T11:47:24.722137+05:00",
      "age_min": 32.4
    },
    {
      "hash": "c9d65ae21e41335394450231002ce8f1",
      "title": "Zimbabwean football star survives gun attack in South Africa",
      "summary": "South African police say they are investigating a case of attempted murder but that no arrests have been made so far.",
      "link": "https://www.bbc.co.uk/news/articles/c1my1rvy28do?at_medium=RSS&at_campaign=rss",
      "source": "BBC World",
      "score": 8,
      "weight": 4,
      "status": "new",
      "ts": "2026-07-07T15:35:25.316049+05:00",
      "age_min": 22.1
    },
    {
      "hash": "ec5a00cdeec27ec19eee38edf26ee255",
      "title": "Shell sees boost from oil price spike amid Iran war , but gas production hit",
      "summary": "",
      "link": "https://www.fenlandcitizen.co.uk/national/shell-sees-boost-from-oil-price-spike-amid-iran-war-but-gas-production-hit-168959/",
      "source": "GDELT/ENERGY",
      "score": 8,
      "weight": 4,
      "status": "new",
      "ts": "2026-07-07T15:34:31.840510+05:00",
      "age_min": 49.5
    },
    {
      "hash": "cd98034236e89a2a1ef5a5c221289dcb",
      "title": "Shell sees boost from oil price spike amid Iran war , but gas production hit",
      "summary": "",
      "link": "https://www.malverngazette.co.uk/news/national/26257970.shell-sees-boost-oil-price-spike-amid-iran-war-gas-production-hit/",
      "source": "GDELT/ENERGY",
      "score": 8,
      "weight": 4,
      "status": "new",
      "ts": "2026-07-07T15:03:50.468159+05:00",
      "age_min": 33.8
    },
    {
      "hash": "6f41b870d960ff3d875500b97a7c2bf6",
      "title": "Война , 7 июля . Как студенты из таежного поселка гибнут на войне . Буданов : На данный момент угроз со стороны Беларуси нет",
      "summary": "",
      "link": "http://gazetaby.com/post/vojna-7-iyulya-kak-studenty-iz-taezhnogo-poselka-gibnut-na-vojne-chto-/215111/",
      "source": "GDELT/CONFLICTS",
      "score": 8,
      "weight": 4,
      "status": "new",
      "ts": "2026-07-07T15:01:49.921607+05:00",
      "age_min": 31.8
    },
    {
      "hash": "badb7c22da1c33a9c0b7349a9def6cee",
      "title": "CCP Ballistic Missile Test Draws Condemnation From Global Leaders",
      "summary": "",
      "link": "https://www.theepochtimes.com/world/ccps-ballistic-missile-test-draws-condemnation-from-global-leaders-6058305",
      "source": "GDELT/CONFLICTS",
      "score": 8,
      "weight": 4,
      "status": "new",
      "ts": "2026-07-07T14:32:05.553782+05:00",
      "age_min": 47.1
    },
    {
      "hash": "ce8e49a06a7f8a6a2bb49dd71157a646",
      "title": "China test - launches a ballistic missile in the South Pacific and raises regional concerns",
      "summary": "",
      "link": "https://wnyc.org/npr/nx-s1-5884537",
      "source": "GDELT/CONFLICTS",
      "score": 8,
      "weight": 4,
      "status": "new",
      "ts": "2026-07-07T14:32:05.552836+05:00",
      "age_min": 47.1
    },
    {
      "hash": "861d849e9167762801291740c1fdb1c1",
      "title": "Why the next few months could reshape the Ukraine war , according to NATO",
      "summary": "",
      "link": "https://www.moneycontrol.com/world/why-the-next-few-months-could-reshape-the-ukraine-war-according-to-nato-article-13967949.html",
      "source": "GDELT/CONFLICTS",
      "score": 8,
      "weight": 4,
      "status": "new",
      "ts": "2026-07-07T14:32:05.551472+05:00",
      "age_min": 47.1
    },
    {
      "hash": "6dc393bfe31b5acdd35c9dc71df9ac40",
      "title": "LNG Tanker Attack Threatens Qatar’s Efforts to Revive Hormuz Exports",
      "summary": "A projectile hit the Al Rekayyat gas carrier on Tuesday, with the repercussions reverberating through the global gas market.",
      "link": "https://www.bloomberg.com/news/newsletters/2026-07-07/attack-on-tanker-threatens-qatar-s-efforts-to-revive-lng-exports",
      "source": "Bloomberg",
      "score": 8,
      "weight": 4,
      "status": "new",
      "ts": "2026-07-07T14:18:00.835470+05:00",
      "age_min": 8.6
    },
    {
      "hash": "d4c7ad98b599cce75eab2c442c9d7077",
      "title": "Shell sees boost from oil price spike amid Iran war , but gas production hit",
      "summary": "",
      "link": "https://www.andoveradvertiser.co.uk/news/national/26257970.shell-sees-boost-oil-price-spike-amid-iran-war-gas-production-hit/",
      "source": "GDELT/ENERGY",
      "score": 8,
      "weight": 4,
      "status": "new",
      "ts": "2026-07-07T14:17:20.053644+05:00",
      "age_min": 32.3
    },
    {
      "hash": "28f0bfe60d1c7fed2f0b1a76f03597c6",
      "title": "Война дело серьезное : что может стоять за последними заявлениями Кремля - БлокнотРУ - Новости СВО . СВО . Когда закончится СВО ? Новости СВО на сегодня . СВО новости . Новости СВО на сегодня свежие читать бесплатно . СВО последние новости . Новости ...",
      "summary": "",
      "link": "https://bloknot.ru/v-mire/vojna-delo-sereznoe-chto-mozhet-stoyat-za-poslednimi-zayavleniyami-kremlya-1525641.html",
      "source": "GDELT/RUSSIA_UA",
      "score": 8,
      "weight": 4,
      "status": "new",
      "ts": "2026-07-07T13:33:44.473732+05:00",
      "age_min": 78.7
    },
    {
      "hash": "6ef50a7761fd59b2943ef24bd0000971",
      "title": "As they escalate war against Russia , imperialist powers greenlight Erdoğan police - state crackdown",
      "summary": "",
      "link": "https://www.wsws.org/en/articles/2026/07/07/amui-j07.html",
      "source": "GDELT/RUSSIA_UA",
      "score": 8,
      "weight": 4,
      "status": "new",
      "ts": "2026-07-07T13:16:11.151690+05:00",
      "age_min": 61.2
    },
    {
      "hash": "5bece13dcf0eab83c6898f14d68f2c1a",
      "title": "Trump says resolution in Ukraine war closer after talks",
      "summary": "",
      "link": "https://www.standard.net.au/story/9305827/trump-says-resolution-in-ukraine-war-closer-after-talks/",
      "source": "GDELT/RUSSIA_UA",
      "score": 8,
      "weight": 4,
      "status": "new",
      "ts": "2026-07-07T13:16:11.147406+05:00",
      "age_min": 61.2
    },
    {
      "hash": "2f546e69b54b120bd6924cd9eecffc9f",
      "title": "Ukraine War , Day 1 , 595 : Zelensky - Putin  Fears For His Life",
      "summary": "",
      "link": "https://eaworldview.com/2026/07/ukraine-war-zelensky-putin-fears-for-his-life/",
      "source": "GDELT/RUSSIA_UA",
      "score": 8,
      "weight": 4,
      "status": "new",
      "ts": "2026-07-07T13:16:11.145299+05:00",
      "age_min": 46.2
    },
    {
      "hash": "2ad47f69fe96c0b6d0cbc062d50f8fa5",
      "title": "Lebanon returnees rebuild amid fears of renewed war",
      "summary": "",
      "link": "https://www.middle-east-online.com/en/lebanons-returnees-rebuild-amid-fears-renewed-war",
      "source": "GDELT/MIDEAST",
      "score": 8,
      "weight": 4,
      "status": "new",
      "ts": "2026-07-07T12:04:40.238814+05:00",
      "age_min": 34.7
    },
    {
      "hash": "f953af22f8c135cf76dcdb0461a1f482",
      "title": "China conducts rare submarine - launched ballistic missile test",
      "summary": "",
      "link": "http://www.australiannews.net/news/279171720/china-conducts-rare-submarine-launched-ballistic-missile-test",
      "source": "GDELT/CONFLICTS",
      "score": 8,
      "weight": 4,
      "status": "new",
      "ts": "2026-07-07T12:04:05.105134+05:00",
      "age_min": 34.1
    },
    {
      "hash": "8289ab23709b0c641b9bae1ba07e90a7",
      "title": "Trump says resolution in Ukraine war closer after talks",
      "summary": "",
      "link": "https://www.sconeadvocate.com.au/story/9305827/trump-says-resolution-in-ukraine-war-closer-after-talks/",
      "source": "GDELT/RUSSIA_UA",
      "score": 8,
      "weight": 4,
      "status": "new",
      "ts": "2026-07-07T11:47:24.726639+05:00",
      "age_min": 47.4
    },
    {
      "hash": "5a0a00d76b0e83f4c538aaf7b939dbd5",
      "title": "China conducts rare submarine - launched ballistic missile test",
      "summary": "",
      "link": "http://www.heraldglobe.com/news/279171720/china-conducts-rare-submarine-launched-ballistic-missile-test",
      "source": "GDELT/CONFLICTS",
      "score": 8,
      "weight": 4,
      "status": "new",
      "ts": "2026-07-07T11:46:30.889578+05:00",
      "age_min": 31.5
    },
    {
      "hash": "04b882f3477c0954298a326182066e87",
      "title": "Peter Schiff Predicts Silver at $200 and Dollar Collapse - Discovery Alert",
      "summary": "Peter Schiff Predicts Silver at $200 and Dollar Collapse&nbsp;&nbsp;Discovery Alert",
      "link": "https://news.google.com/rss/articles/CBMijAFBVV95cUxQSmZkZDJjYkxVbmpLMEJQWDQ0U0tEbF80aEZabHFkc0c2Q3hybkNFdmY4TzJWU2ZHZTU5QXNtS0hPbkZrbFZBNVg3Z0xlQTY4ZUNnT0E4d05NZWFRU0MwaWdZU3UzYXNtUnd0UTZ6dUlYT19MWmZ2MjROX0NRcVFXaDc3NEhqVDdRemc2dw?oc=5",
      "source": "GNews/CentralBanks",
      "score": 10,
      "weight": 3,
      "status": "new",
      "ts": "2026-07-07T15:05:05.003018+05:00",
      "age_min": 8.8
    },
    {
      "hash": "12f90b813802c80c7b988c645ec1410a",
      "title": "Why China Fired a Long-Range Missile Into the Pacific",
      "summary": "Beijing had long tested nuclear missiles only within its borders. A rare launch over an ocean shows it is determined to narrow the gap with the United States.",
      "link": "https://www.nytimes.com/2026/07/07/world/asia/china-missile-test-submarine-pacific.html",
      "source": "NYT World",
      "score": 10,
      "weight": 3,
      "status": "new",
      "ts": "2026-07-07T15:04:42.639709+05:00",
      "age_min": 9.6
    },
    {
      "hash": "d1fd51ba4aaa31c184624a2b77f38f94",
      "title": "Estonia Won the War on Fentanyl. What Came Next Was Even Worse.",
      "summary": "By 2018, fentanyl overdoses in Estonia had plummeted. But powerful new drugs are appearing fast, with the authorities racing to respond.",
      "link": "https://www.nytimes.com/2026/07/07/world/europe/estonia-won-the-war-on-fentanyl-what-came-next-was-even-worse.html",
      "source": "NYT World",
      "score": 10,
      "weight": 3,
      "status": "new",
      "ts": "2026-07-07T14:18:01.550142+05:00",
      "age_min": 17.4
    },
    {
      "hash": "2e1e9715c772780a459a8e9f788171ac",
      "title": "With a Fragile Ceasefire under Threat, What Future for the Strait of Hormuz?",
      "summary": "The U.S.-Israeli war with Iran prompted Tehran to close the Strait of Hormuz, allowing only selected ships to pass through. In this Q&amp;A, Crisis Group experts Yasmine Farouk, Chris Newton and Ali Vaez consider what could come next in this vital maritime trade corridor.",
      "link": "https://www.crisisgroup.org/qna/global/iran-israelpalestine-united-states/fragile-ceasefire-under-threat-what-future-strait-hormuz",
      "source": "Crisis Group",
      "score": 10,
      "weight": 3,
      "status": "new",
      "ts": "2026-07-07T12:17:54.558005+05:00",
      "age_min": 0
    },
    {
      "hash": "91603969616d2f431279bbe86edc812b",
      "title": "A Once-Great Copper Miner Faces a Reckoning Just as AI Power Demand Soars",
      "summary": "Chile’s Codelco, facing scrutiny for a fatal accident and inflated production figures, is struggling under $25 billion of debt.",
      "link": "https://www.bloomberg.com/news/articles/2026-07-07/codelco-confronts-debt-output-concerns-as-copper-demand-soars-on-ai",
      "source": "Bloomberg",
      "score": 7,
      "weight": 4,
      "status": "new",
      "ts": "2026-07-07T15:04:41.709210+05:00",
      "age_min": 4.3
    },
    {
      "hash": "41c1b182a48d12add74b1dd149f61df9",
      "title": "Jeffrey Donaldson mentor Enoch Powell  treated child abuse victim as sex slave  – The Irish News",
      "summary": "",
      "link": "https://www.irishnews.com/news/northern-ireland/jeffrey-donaldson-mentor-enoch-powell-treated-child-abuse-victim-as-sex-slave-NO3CLDAEPBGILIEH6M5GIVQQYA/",
      "source": "GDELT/FED_ECB",
      "score": 7,
      "weight": 4,
      "status": "new",
      "ts": "2026-07-07T15:03:36.660344+05:00",
      "age_min": 78.6
    },
    {
      "hash": "ce0685d50cceb225ffa4f12def1e7b93",
      "title": "Ukrainians send 100 , 000 troops to Kramatorsk , set up dragon teeth - Unprecedented from Russia : Mobilization",
      "summary": "",
      "link": "https://www.bankingnews.gr/diethni/articles/886613/ukrainians-send-100-000-troops-to-kramatorsk-set-up-dragon-s-teeth-unprecedented-from-russia-mobilization",
      "source": "GDELT/CONFLICTS",
      "score": 7,
      "weight": 4,
      "status": "new",
      "ts": "2026-07-07T15:01:49.925755+05:00",
      "age_min": 31.8
    },
    {
      "hash": "b288b1b6bfba49b889e104b2cbabaf09",
      "title": "Oil Prices Rise as Strait of Hormuz Risks Offset OPEC+ Supply Increase",
      "summary": "",
      "link": "http://www.econotimes.com/Oil-Prices-Rise-as-Strait-of-Hormuz-Risks-Offset-OPEC-Supply-Increase-1746084",
      "source": "GDELT/ENERGY",
      "score": 7,
      "weight": 4,
      "status": "new",
      "ts": "2026-07-07T14:17:20.052281+05:00",
      "age_min": 77.3
    },
    {
      "hash": "cbf1a9394407bc8699efd10ff65b893d",
      "title": "Qatari gas tanker hit in Strait of Hormuz",
      "summary": "Al Rekayyat comes under fire close to coast of Oman",
      "link": "https://www.ft.com/content/0a1c6329-2be0-4d7a-b7ab-82f81511bde2",
      "source": "FT",
      "score": 7,
      "weight": 4,
      "status": "new",
      "ts": "2026-07-07T13:47:44.388575+05:00",
      "age_min": 28.5
    },
    {
      "hash": "e2a373c520fd1052f0667cba3cf533d9",
      "title": "Global LNG trade hit record in 2025 , but Middle East conflict clouds outlook , IGU says",
      "summary": "",
      "link": "https://www.thehindubusinessline.com/markets/commodities/global-lng-trade-hit-record-in-2025-but-middle-east-conflict-clouds-outlook-igu-says/article71191995.ece",
      "source": "GDELT/ENERGY",
      "score": 7,
      "weight": 4,
      "status": "new",
      "ts": "2026-07-07T11:49:03.445396+05:00",
      "age_min": 64.1
    },
    {
      "hash": "8aeae48c0fe9a079ab320efc8a308aff",
      "title": "Seoul launches new team to counter North Korean drone and nuclear threats",
      "summary": "",
      "link": "https://www.nknews.org/2026/07/seoul-launches-new-team-to-counter-north-korean-drone-and-nuclear-threats/",
      "source": "GDELT/CYBER",
      "score": 9,
      "weight": 3,
      "status": "new",
      "ts": "2026-07-07T15:17:14.079285+05:00",
      "age_min": 47.2
    },
    {
      "hash": "97ca3780e31c5dc2374659f7a759f90a",
      "title": "France Cuts 2026 GDP Forecast Due to Budget Delay, Iran Conflict",
      "summary": "The French government is lowering its growth forecast for the year to 0.7% after a delayed budget and the Middle East conflict held back output, Finance Minister Roland Lescure told Le Parisien newspaper.",
      "link": "https://www.bloomberg.com/news/articles/2026-07-07/france-cuts-2026-gdp-forecast-due-to-budget-delay-iran-conflict",
      "source": "Bloomberg",
      "score": 6,
      "weight": 4,
      "status": "new",
      "ts": "2026-07-07T15:35:24.448391+05:00",
      "age_min": 26.7
    },
    {
      "hash": "09b3ee0d08bdc908f6b331dc13149d26",
      "title": "Kevin Warsh juega a las escondidas con la suba de tasas",
      "summary": "",
      "link": "https://www.diariopanorama.com/noticia/558698/kevin-warsh-juega-escondidas-suba-tasas",
      "source": "GDELT/MACRO",
      "score": 6,
      "weight": 4,
      "status": "new",
      "ts": "2026-07-07T15:35:20.998225+05:00",
      "age_min": 35.3
    },
    {
      "hash": "fd5f0d0f490ac2e06dadf64b4a27d583",
      "title": "European gas prices jump after Hormuz ship attack",
      "summary": "",
      "link": "https://news.az/news/european-gas-prices-jump-after-hormuz-ship-attack",
      "source": "GDELT/ENERGY",
      "score": 6,
      "weight": 4,
      "status": "new",
      "ts": "2026-07-07T15:34:31.839940+05:00",
      "age_min": 49.5
    },
    {
      "hash": "bf65dc873aea3334edb57df090c1b006",
      "title": "Monaco bomb attack suspect  found shot dead near Kyiv  after days on the run",
      "summary": "",
      "link": "https://www.mirror.co.uk/news/world-news/monaco-bomb-suspect-dead-ukraine-37396842",
      "source": "GDELT/TERRORISM",
      "score": 6,
      "weight": 4,
      "status": "new",
      "ts": "2026-07-07T15:33:12.862832+05:00",
      "age_min": 33.2
    },
    {
      "hash": "5b7d5ef17e30dcc4aedcd0f865527cd5",
      "title": "A Long Gulf War Can Starve the World. A Hormuz Transit Deal Could Save Millions.",
      "summary": "",
      "link": "https://www.crisisgroup.org/opd/global/iran-israelpalestine-united-states/long-gulf-war-can-starve-world-hormuz-transit-deal-could-save-millions",
      "source": "Crisis Group",
      "score": 8,
      "weight": 3,
      "status": "new",
      "ts": "2026-07-07T15:17:52.855211+05:00",
      "age_min": 0
    },
    {
      "hash": "34cd2438553a488c95b887c7ebed0dbc",
      "title": "EU and NATO Members Grapple with War in Iran",
      "summary": "This week on War &amp; Peace, Olga speaks with Crisis Group’s head of EU Affairs, Lisa Musiol, about how the EU, its members and European members of NATO have responded to the U.S.-Israeli war with Iran and what it reveals about EU foreign policy and its constraints.",
      "link": "https://www.crisisgroup.org/pod/europe/eu-and-nato-members-grapple-war-iran",
      "source": "Crisis Group",
      "score": 8,
      "weight": 3,
      "status": "new",
      "ts": "2026-07-07T15:17:52.854160+05:00",
      "age_min": 0
    },
    {
      "hash": "c80745885752ea57734e77c90646f6dc",
      "title": "Deloitte warns Australian economy facing longest period of sub - par growth since 1990s recession",
      "summary": "",
      "link": "https://www.watoday.com.au/politics/federal/worst-since-the-1990s-recession-alarm-over-australia-s-sluggish-growth-20260707-p60d68.html",
      "source": "GDELT/FED_ECB",
      "score": 6,
      "weight": 4,
      "status": "new",
      "ts": "2026-07-07T15:03:36.657691+05:00",
      "age_min": 33.6
    },
    {
      "hash": "8d261d04529305bf565d6350b4275e1d",
      "title": "Saudi Arabia mulls big new plan , eyes post - war oil route reset to bypass volatile Hormuz",
      "summary": "",
      "link": "https://economictimes.indiatimes.com/news/international/saudi-arabia/saudi-arabia-mulls-big-new-plan-eyes-post-war-oil-route-reset-to-bypass-volatile-hormuz/articleshow/132233409.cms",
      "source": "GDELT/SANCTIONS",
      "score": 8,
      "weight": 3,
      "status": "new",
      "ts": "2026-07-07T14:33:28.625757+05:00",
      "age_min": 93.5
    },
    {
      "hash": "241aed723ff6a4d1f46c6bd62c82b1d8",
      "title": "Ziarat terror attack : 9 policemen martyred",
      "summary": "",
      "link": "https://www.samaa.tv/2087353143-ziarat-terrorism-9-policemen-martyred-in-checkpost-attack",
      "source": "GDELT/TERRORISM",
      "score": 6,
      "weight": 4,
      "status": "new",
      "ts": "2026-07-07T14:16:13.971930+05:00",
      "age_min": 76.2
    },
    {
      "hash": "73a3f27beb291984f13a4fcd504cde71",
      "title": "After Iran war upheaval, global shipping eyes return to status quo",
      "summary": "Industry known for its resilience is likely to emerge from war relatively unchanged, analysts say.",
      "link": "https://www.aljazeera.com/economy/2026/7/7/after-iran-war-upheaval-global-shipping-eyes-return-to-status-quo?traffic_source=rss",
      "source": "Al Jazeera",
      "score": 8,
      "weight": 3,
      "status": "new",
      "ts": "2026-07-07T14:05:37.102390+05:00",
      "age_min": 34.5
    },
    {
      "hash": "7c488e42bafb28051c7ccaa1248fcf67",
      "title": "Oil prices rise after report of Iranian attack on commercial ships in Strait of Hormuz",
      "summary": "Brent and U.S. crude futures rose after a report of an Iranian attack on commercial ships in the Strait of Hormuz.",
      "link": "https://www.cnbc.com/2026/07/07/oil-prices-iran-strait-hormuz.html",
      "source": "CNBC",
      "score": 8,
      "weight": 3,
      "status": "new",
      "ts": "2026-07-07T13:35:32.043210+05:00",
      "age_min": 12.2
    },
    {
      "hash": "bf0d79523cc235330cce251bcf6b4a3e",
      "title": "Russia touts ‘war with NATO’ amid losses in Ukraine",
      "summary": "As Russia faces challenges on the frontlines and at home, President Putin&#039;s backers decry Kyiv&#039;s Western allies.",
      "link": "https://www.aljazeera.com/news/2026/7/7/russia-touts-war-with-nato-amid-losses-in-ukraine?traffic_source=rss",
      "source": "Al Jazeera",
      "score": 8,
      "weight": 3,
      "status": "new",
      "ts": "2026-07-07T13:35:31.885196+05:00",
      "age_min": 12.9
    },
    {
      "hash": "967331df4a698718e0f3a13870fe49fe",
      "title": "The likely loser in Gulf's post-war race for oil market share - ET EnergyWorld",
      "summary": "The likely loser in Gulf's post-war race for oil market share&nbsp;&nbsp;ET EnergyWorld",
      "link": "https://news.google.com/rss/articles/CBMiywFBVV95cUxObVl3MVVncmNNekRmaTdNOXFKODBMOUk2Nk5mV2lVOTJ6Q0NUcDhkdnVjSE5QNUpmUDJBS2VhRmQ1aFQ0emFNOTBWZDZqRFdNWkxXajJtTzl6T0cta2hoazFuTEpHcXFDVHhiQ1M3dHZtUHp0a2E4elZjUUxjSWxzbVNnSmdyb0F5bEg2aUp2UkYzcmgwaXJILVZCaFJCOVN3LXpGbk1HNTg5UVZmMzgzNWluN2N1WERlT3JlLWl4SEdpZEl2ZkR2ZjNxd9IB0AFBVV95cUxORWhjQWxjcEc0YW41X1NUVUZRWWFMRU9uZ29VdmtLOG1pY2lvMTVaYzN6TmY5RzE4ZkJYTjRwNzVjUzZqV2g4ODU1UHFRR0NvNjk5NHVNa0R1NkxmLUxZb0xHS1d1Sm1PaVdDdE1OVnY1d2RNLVExcVRreVRpeWZ6QXF0WnZFTHB3dWtpbE5HbVg2TlR4UkZad3IybVQ0SVp3M20zUVZVU1dHQ21oZ2NuNWhWZ1h4WFEyUFdlZnE4T1F5bEE3RFZYMkU4LWRkMzQ0?oc=5",
      "source": "GNews/Oil",
      "score": 8,
      "weight": 3,
      "status": "new",
      "ts": "2026-07-07T12:10:30.985578+05:00",
      "age_min": 10.3
    },
    {
      "hash": "0223208f8ca4a365a713fe3033b477a6",
      "title": "Ukraine Drone Attack : Ukraine launches 400+ drones at Moscow after deadly Russian strikes ahead of Nato summit",
      "summary": "",
      "link": "https://timesofindia.indiatimes.com/world/europe/ukraine-launches-400-drones-at-moscow-after-deadly-russian-strikes-ahead-of-nato-summit/articleshow/132230065.cms",
      "source": "GDELT/RUSSIA_UA",
      "score": 6,
      "weight": 4,
      "status": "new",
      "ts": "2026-07-07T11:47:24.724078+05:00",
      "age_min": 92.4
    }
  ]
}